ukds/__init__.py
ukds/data_dictionary.py
ukds/data_table.py
ukds-0.0.1.dist-info/LICENSE
ukds-0.0.1.dist-info/METADATA
ukds-0.0.1.dist-info/WHEEL
ukds-0.0.1.dist-info/top_level.txt
ukds-0.0.1.dist-info/RECORD
