Metadata-Version: 2.1
Name: ukds
Version: 0.0.1
Summary: A Python package for working with datasets from the UK Data Service (UKDS)
Home-page: https://github.com/building-energy/ukds
Author: Steven K Firth
Author-email: s.k.firth@lboro.ac.uk
License: UNKNOWN
Platform: UNKNOWN
Classifier: Programming Language :: Python :: 3
Classifier: License :: OSI Approved :: MIT License
Classifier: Operating System :: OS Independent
Requires-Python: >=3.6
